LICENSE
README.md
fakenos/__init__.py
fakenos/core/__init__.py
fakenos/core/fakenos.py
fakenos/core/host.py
fakenos/core/nos.py
fakenos/core/pydantic_models.py
fakenos/core/servers.py
fakenos/plugins/__init__.py
fakenos/plugins/nos/__init__.py
fakenos/plugins/nos/platforms_py/__init__.py
fakenos/plugins/nos/platforms_py/arista_eos.py
fakenos/plugins/nos/platforms_py/cisco_ios.py
fakenos/plugins/nos/platforms_yaml/alcatel_aos.yaml
fakenos/plugins/nos/platforms_yaml/alcatel_sros.yaml
fakenos/plugins/nos/platforms_yaml/allied_telesis_awplus.yaml
fakenos/plugins/nos/platforms_yaml/arista_eos.yaml
fakenos/plugins/nos/platforms_yaml/aruba_os.yaml
fakenos/plugins/nos/platforms_yaml/avaya_ers.yaml
fakenos/plugins/nos/platforms_yaml/avaya_vsp.yaml
fakenos/plugins/nos/platforms_yaml/broadcom_icos.yaml
fakenos/plugins/nos/platforms_yaml/brocade_fastiron.yaml
fakenos/plugins/nos/platforms_yaml/brocade_netiron.yaml
fakenos/plugins/nos/platforms_yaml/checkpoint_gaia.yaml
fakenos/plugins/nos/platforms_yaml/ciena_saos.yaml
fakenos/plugins/nos/platforms_yaml/cisco_asa.yaml
fakenos/plugins/nos/platforms_yaml/cisco_ftd.yaml
fakenos/plugins/nos/platforms_yaml/cisco_ios.yaml
fakenos/plugins/nos/platforms_yaml/cisco_nxos.yaml
fakenos/plugins/nos/platforms_yaml/cisco_s300.yaml
fakenos/plugins/nos/platforms_yaml/cisco_xr.yaml
fakenos/plugins/nos/platforms_yaml/dell_force10.yaml
fakenos/plugins/nos/platforms_yaml/dell_powerconnect.yaml
fakenos/plugins/nos/platforms_yaml/dlink_ds.yaml
fakenos/plugins/nos/platforms_yaml/eltex.yaml
fakenos/plugins/nos/platforms_yaml/ericsson_ipos.yaml
fakenos/plugins/nos/platforms_yaml/extreme_exos.yaml
fakenos/plugins/nos/platforms_yaml/fortinet.yaml
fakenos/plugins/nos/platforms_yaml/hp_comware.yaml
fakenos/plugins/nos/platforms_yaml/hp_procurve.yaml
fakenos/plugins/nos/platforms_yaml/huawei_smartax.yaml
fakenos/plugins/nos/platforms_yaml/huawei_vrp.yaml
fakenos/plugins/nos/platforms_yaml/ipinfusion_ocnos.yaml
fakenos-1.0.1.dist-info/LICENSE
fakenos-1.0.1.dist-info/METADATA
fakenos-1.0.1.dist-info/WHEEL
fakenos-1.0.1.dist-info/entry_points.txt
fakenos-1.0.1.dist-info/RECORD
