Metadata-Version: 2.1
Name: fakenos
Version: 1.0.1
Summary: Fake Network Operating System
License: MIT
Keywords: NetworkAutomation,Testing,SSH
Author: Denis Mulyalin
Author-email: d.mulyalin@gmail.com
Maintainer: Denis Mulyalin
Maintainer-email: d.mulyalin@gmail.com
Requires-Python: >=3.8,<3.13
Classifier: License :: OSI Approved :: MIT License
Classifier: Operating System :: POSIX :: Linux
Classifier: Programming Language :: Python :: 3
Classifier: Programming Language :: Python :: 3.8
Classifier: Programming Language :: Python :: 3.9
Classifier: Programming Language :: Python :: 3.10
Classifier: Programming Language :: Python :: 3.11
Classifier: Programming Language :: Python :: 3.12
Classifier: Topic :: Utilities
Provides-Extra: test
Requires-Dist: detect (==2020.12.*)
Requires-Dist: paramiko (<4.0)
Requires-Dist: pydantic (<3.0)
Requires-Dist: pyyaml (<7.0)
